graphemy-1.1.2.dist-info/METADATA
graphemy-1.1.2.dist-info/WHEEL
graphemy-1.1.2.dist-info/entry_points.txt
graphemy-1.1.2.dist-info/licenses/LICENSE
graphemy/__init__.py
graphemy/database/__init__.py
graphemy/database/operations.py
graphemy/database/utils.py
graphemy/dl.py
graphemy/models.py
graphemy/router.py
graphemy/schemas/__init__.py
graphemy/schemas/generators.py
graphemy/schemas/models.py
graphemy/setup.py
graphemy-1.1.2.dist-info/RECORD
