Metadata-Version: 2.1
Name: graphemy
Version: 1.1.2
Summary: A Python library for integrating SQLModel and Strawberry, providing a seamless GraphQL integration with FastAPI and advanced features for database interactions.
Author-Email: Matheus Doreto <matheusdoreto.md@gmail.com>
License: MIT
Classifier: Development Status :: 5 - Production/Stable
Classifier: Topic :: Database
Classifier: Topic :: Database :: Database Engines/Servers
Classifier: Intended Audience :: Developers
Classifier: Framework :: FastAPI
Classifier: Programming Language :: Python :: 3.12
Classifier: Natural Language :: English
Project-URL: Documentation, https://graphemy.readthedocs.io/en/latest/
Project-URL: Repository, https://github.com/MDoreto/graphemy
Project-URL: Bug Tracker, https://github.com/MDoreto/graphemy/issues
Project-URL: homepage, https://github.com/MDoreto/graphemy
Project-URL: repository, https://github.com/MDoreto/graphemy
Project-URL: documentation, https://graphemy.readthedocs.io/en/latest/
Requires-Python: <4.0,>=3.12
Requires-Dist: sqlmodel<1.0.0,>=0.0.22
Requires-Dist: strawberry-graphql[debug-server]<1.0.0,>=0.240.0
Requires-Dist: fastapi<1.0.0,>=0.114.0
